README.txt
setup.py
collective/__init__.py
collective.contentrules.parentchild.egg-info/PKG-INFO
collective.contentrules.parentchild.egg-info/SOURCES.txt
collective.contentrules.parentchild.egg-info/dependency_links.txt
collective.contentrules.parentchild.egg-info/entry_points.txt
collective.contentrules.parentchild.egg-info/namespace_packages.txt
collective.contentrules.parentchild.egg-info/not-zip-safe
collective.contentrules.parentchild.egg-info/requires.txt
collective.contentrules.parentchild.egg-info/top_level.txt
collective/contentrules/__init__.py
collective/contentrules/parentchild/__init__.py
collective/contentrules/parentchild/autotransition.py
collective/contentrules/parentchild/child.py
collective/contentrules/parentchild/configure.zcml
collective/contentrules/parentchild/parenttransition.py
collective/contentrules/parentchild/tests/__init__.py
collective/contentrules/parentchild/tests/base.py
collective/contentrules/parentchild/tests/test_autotransition.py
collective/contentrules/parentchild/tests/test_child.py
collective/contentrules/parentchild/tests/test_parenttransition.py
docs/HISTORY.txt
docs/INSTALL.txt
docs/LICENSE.GPL
docs/LICENSE.txt