Metadata-Version: 1.0
Name: collective.contentrules.parentchild
Version: 1.0b1
Summary: Content rules conditions and actions for expressing parent/child object relationships
Home-page: http://pypi.python.org/pypi/collective.contentrules.parentchild
Author: Martin Aspeli
Author-email: optilude@gmail.com
License: GPL
Keywords: plone content rules
Platform: UNKNOWN
Classifier: Framework :: Plone
Classifier: Programming Language :: Python
Classifier: Topic :: Software Development :: Libraries :: Python Modules
